jax_pt-1.0.0.dist-info/licenses/LICENSE
jaxpt/JAXPT.py
jaxpt/__init__.py
jaxpt/jax_utils.py
jax_pt-1.0.0.dist-info/METADATA
jax_pt-1.0.0.dist-info/WHEEL
jax_pt-1.0.0.dist-info/top_level.txt
jax_pt-1.0.0.dist-info/RECORD
