Metadata-Version: 2.4
Name: jax-pt
Version: 1.0.0
Summary: JAX-accelerated FAST-PT for computing perturbation theory power spectra
Author-email: Vincent Schacknies <vincent.schacknies@icloud.com>
License: MIT
Project-URL: Homepage, https://github.com/vschac/jax-pt
Project-URL: Repository, https://github.com/vschac/jax-pt
Project-URL: Documentation, https://github.com/vschac/JAX-PT/blob/main/README.md
Project-URL: Bug Tracker, https://github.com/vschac/jax-pt/issues
Keywords: cosmology,perturbation-theory,jax,gpu,astrophysics,fastpt
Classifier: Development Status :: 4 - Beta
Classifier: Intended Audience :: Science/Research
Classifier: License :: OSI Approved :: MIT License
Classifier: Programming Language :: Python :: 3
Classifier: Programming Language :: Python :: 3.8
Classifier: Programming Language :: Python :: 3.9
Classifier: Programming Language :: Python :: 3.10
Classifier: Programming Language :: Python :: 3.11
Classifier: Programming Language :: Python :: 3.12
Classifier: Topic :: Scientific/Engineering :: Astronomy
Classifier: Topic :: Scientific/Engineering :: Physics
Requires-Python: >=3.8
License-File: LICENSE
Requires-Dist: fast-pt>=4.0.0
Requires-Dist: jax>=0.4.16
Requires-Dist: jaxlib>=0.4.16
Requires-Dist: jax-cosmo>=0.1.0
Requires-Dist: setuptools
Requires-Dist: numpy>=1.17
Requires-Dist: scipy>=1.2
Provides-Extra: dev
Requires-Dist: pytest; extra == "dev"
Requires-Dist: memory_profiler; extra == "dev"
Requires-Dist: matplotlib; extra == "dev"
Requires-Dist: colorama; extra == "dev"
Requires-Dist: build; extra == "dev"
Requires-Dist: twine; extra == "dev"
Dynamic: license-file
